[
  {
    "Source URL": "https://www.aimguwahati.edu.in/",
    "Page Title": "AIM \u00e2\u20ac\u201c The best management college in Assam",
    "Facebook": "https://www.facebook.com/assaminstituteofmanagementguwahati",
    "Instagram": "https://www.instagram.com/aimguwahati?utm_source=ig_web_button_share_sheet&igsh=ZDNlZDc0MzIxNw==",
    "YouTube": "https://www.youtube.com/@assaminstituteofmanagement1807",
    "Phone": [
      "8474884123"
    ],
    "Email": [
      "mail@aimguwahati.edu.in"
    ],
    "Last Update": "2025-07-25 13:15:54.580502+00:00",
    "Twitter": "https://x.com/aimghy?s=20"
  }
]