[
  {
    "Source URL": "https://www.bknmu.edu.in/",
    "Page Title": "BHAKTA KAVI NARSINH MEHTA UNIVERSITY",
    "Twitter": "https://twitter.com/Bknmu_official?s=08",
    "Facebook": "https://www.facebook.com/bknmujunagadh/",
    "Instagram": "https://www.instagram.com/bknmu_junagadh/",
    "YouTube": "https://www.youtube.com/channel/UCN8LwI7EiXQ_7AYuSTKKtYA/featured",
    "Phone": [
      "0285-2681400"
    ],
    "Email": [
      "info@bknmu.edu.in"
    ],
    "Last Update": "2025-07-25 13:22:38.970699+00:00"
  }
]