[
  {
    "Source URL": "https://english.bmrc.co.in/",
    "Page Title": "Namma Metro",
    "Twitter": "https://twitter.com/cpronammametro",
    "Facebook": "https://www.facebook.com/BMRCL",
    "YouTube": "https://www.youtube.com/channel/UCRakuC4Dqb8ZRUIBgCC4j9Q/featured",
    "Phone": [
      "080-22969400",
      "080-22969200",
      "080 -25191091"
    ],
    "Email": [
      "contactus@bmrc.co",
      "travelhelp@bmrc.co.in"
    ],
    "Last Update": "2025-07-25 13:22:27.140433+00:00"
  }
]