[
  {
    "Source URL": "https://cooperatives.gov.in/en/",
    "Page Title": "National Cooperative Database",
    "Twitter": "https://twitter.com/MinOfCooperatn/",
    "Facebook": "https://www.facebook.com/MinOfCooperatn/",
    "Instagram": "https://www.instagram.com/minofcooperatn/",
    "YouTube": "https://www.youtube.com/MinOfCooperatn",
    "Phone": [
      "011 20909005",
      "011 20862616"
    ],
    "Email": [
      "ncd.dpt-coop@gov.in",
      "ncd.techcoop@gmail.com"
    ],
    "Last Update": "2025-07-25 13:27:21.647683+00:00"
  }
]