[
  {
    "Source URL": "https://doca.gov.in/",
    "Page Title": "Home | Department of Consumer Affairs",
    "Twitter": "http://www.twitter.com/",
    "Facebook": "http://www.facebook.com/",
    "YouTube": "http://www.youtube.com/",
    "Last Update": "2025-07-23 00:31:34.851036"
  },
  {
    "Source URL": "https://lm.doca.gov.in/",
    "Page Title": "Home | Ministry | Department | Legal Metrology",
    "Twitter": "https://twitter.com/thelmindia",
    "Facebook": "https://www.facebook.com/thelmindia",
    "Instagram": "https://instagram.com/thelmindia",
    "YouTube": "https://www.youtube.com/@thelmindia",
    "Last Update": "2025-07-25 14:09:57.408903+00:00"
  }
]