[
  {
    "Source URL": "https://bidplus.gem.gov.in/all-bids/",
    "Page Title": "GeM |    All Bids on GeM",
    "Twitter": "https://twitter.com/GeM_India",
    "Facebook": "https://www.facebook.com/govGeM/",
    "YouTube": "https://www.youtube.com/channel/UC1LaBWVVZv3k23BZApfDlsQ",
    "Last Update": "2023-11-05 14:55:20.646660"
  },
  {
    "Source URL": "https://gem.gov.in/",
    "Page Title": "Government e Marketplace | National Public Procurement Portal",
    "Twitter": "https://twitter.com/GeM_India",
    "Facebook": "https://www.facebook.com/govGeM/",
    "Instagram": "https://www.instagram.com/government.e.marketplace/",
    "YouTube": "https://www.youtube.com/channel/UC1LaBWVVZv3k23BZApfDlsQ",
    "Last Update": "2025-07-25 14:11:56.750219+00:00"
  }
]