[
  {
    "Source URL": "https://gmch.gov.in/",
    "Page Title": "Home | Government Medical College & Hospital , Sector 32, Chandigarh, India",
    "Twitter": "https://www.twitter.com/gmch_32",
    "Facebook": "https://www.facebook.com/Government-Medical-College-and-Hospital-1360910577330500",
    "YouTube": "http://www.youtube.com/channel/UCc4r2ps9bSeThlOW0UOxbJA",
    "Phone": [
      "9465565592",
      "0172-2601023",
      "0172-2609360",
      "0172-2601024",
      "1800180206"
    ],
    "Email": [
      "manoj.vohra@gmch.gov.in",
      "dpgmch-chd@gmch.gov.in"
    ],
    "Last Update": "2025-07-25 14:12:06.957068+00:00"
  }
]