[
  {
    "Source URL": "https://indianarmyveterans.gov.in/",
    "Page Title": "Home Page",
    "Twitter": "https://twitter.com/DIAV20",
    "Facebook": "https://www.facebook.com/IndianArmyVeteransDirectorate/",
    "Phone": [
      "9910964067",
      "01120897639",
      "1800116644",
      "01125664200",
      "01125674066",
      "9910610866",
      "01120897738",
      "01125664100"
    ],
    "Email": [
      "diav.vsk@gov.in",
      "veteranscell-army@nic.in"
    ],
    "Last Update": "2025-07-25 15:24:57.330747+00:00"
  }
]