[
  {
    "Source URL": "https://onlinemaps.surveyofindia.gov.in/",
    "Page Title": "Survey of India",
    "Phone": [
      "+91-135-2970896"
    ],
    "Email": [
      "mtr.soi@gov.in"
    ],
    "Last Update": "2025-07-25 16:59:14.645293+00:00"
  },
  {
    "Source URL": "https://onlinemaps.surveyofindia.gov.in/FreeMapSpecification.aspx/",
    "Page Title": "Survey of India",
    "Phone": [
      "+91-135-2970896"
    ],
    "Email": [
      "mtr.soi@gov.in"
    ],
    "Last Update": "2025-07-25 16:59:14.340892+00:00"
  },
  {
    "Source URL": "https://www.surveyofindia.gov.in/",
    "Page Title": "Survey of India",
    "Twitter": "https://twitter.com/india_soi",
    "Facebook": "https://www.facebook.com/SOIDST",
    "YouTube": "https://www.youtube.com/channel/UCntYNtrSf6eXL3O4yWVBt0w",
    "Phone": [
      "+91-135-2747051",
      "+91-135-2744064"
    ],
    "Email": [
      "helpdesk.soi@gov.in"
    ],
    "Last Update": "2025-07-25 16:59:29.025376+00:00"
  }
]