[
  {
    "Source URL": "https://jansunwai.up.nic.in/",
    "Page Title": "\u091c\u0928\u0938\u0941\u0928\u0935\u093e\u0908 -\u0938\u092e\u093e\u0927\u093e\u0928 |\u0909\u0924\u094d\u0924\u0930 \u092a\u094d\u0930\u0926\u0947\u0936 \u0938\u0930\u0915\u093e\u0930",
    "Twitter": "https://twitter.com/jansunwai_up",
    "Facebook": "https://www.facebook.com/up.IGRS/",
    "Email": [
      "up@gov.in"
    ],
    "Last Update": "2025-07-25 17:03:23.404916+00:00"
  },
  {
    "Source URL": "https://kmc.up.nic.in/",
    "Page Title": "\u0915\u093e\u0928\u092a\u0941\u0930 \u0928\u0917\u0930 \u0928\u093f\u0917\u092e",
    "Twitter": "https://twitter.com/nagarnigamknp",
    "Facebook": "https://www.facebook.com/KanpurMunicipalCorporation",
    "Instagram": "https://www.instagram.com/kmckanpur/",
    "Phone": [
      "1800180515",
      "1800180512",
      "0512-2526004",
      "918001801470"
    ],
    "Last Update": "2025-07-25 17:03:26.620512+00:00"
  },
  {
    "Source URL": "https://lmc.up.nic.in/",
    "Page Title": "LUCKNOW NAGAR NIGAM",
    "Twitter": "https://twitter.com/LMC_IECofficial?t=MlOIiVMKj6NJeM6miRGjyg&s=09",
    "Facebook": "https://www.facebook.com/LMC.Lucknow?mibextid=ZbWKwL",
    "Instagram": "https://instagram.com/lmc.lucknow?igshid=ZDdkNTZiNTM=",
    "YouTube": "https://youtube.com/@LucknowMunicipalCorporation",
    "Phone": [
      "6389200005"
    ],
    "Last Update": "2025-07-25 17:03:26.390595+00:00"
  },
  {
    "Source URL": "https://localbodies.up.nic.in/",
    "Page Title": "Home : \u0909\u0924\u094d\u0924\u0930 \u092a\u094d\u0930\u0926\u0947\u0936 \u0938\u094d\u0925\u093e\u0928\u0940\u092f \u0928\u093f\u0915\u093e\u092f \u0928\u093f\u0926\u0947\u0936\u093e\u0932\u092f : GoUP",
    "Twitter": "https://twitter.com/ulb_up",
    "Facebook": "https://www.facebook.com/pg/Directorate-ULB-UP-113789363514901/about/?ref=page_internal",
    "Last Update": "2025-07-25 17:03:25.975367+00:00"
  },
  {
    "Source URL": "https://niveshmitra.up.nic.in/",
    "Page Title": "Nivesh Mitra",
    "Twitter": "https://twitter.com/_InvestUP?t=XEu6lIxeFBjHhPBLo9CrxQs=09",
    "Facebook": "https://www.facebook.com/InvestUPNew/",
    "YouTube": "https://www.youtube.com/@easeofdoingbusinessudyogba4129",
    "Phone": [
      "0522 6923000"
    ],
    "Email": [
      "info@investup.org.in"
    ],
    "Last Update": "2025-07-25 17:03:27.008969+00:00"
  },
  {
    "Source URL": "https://panchayatiraj.up.nic.in/",
    "Page Title": "Panchayati Raj Uttar Pradesh",
    "Twitter": "https://twitter.com/uppanchayatiraj?ref_src=twsrc%5Etfw",
    "Facebook": "https://facebook.com/up.panchayatiraj",
    "YouTube": "https://www.youtube.com/c/DepartmentofPanchayatiRaj",
    "Email": [
      "up.panchayatiraj@gmail.com",
      "panchraj@nic.in"
    ],
    "Last Update": "2025-07-25 17:03:33.824427+00:00"
  },
  {
    "Source URL": "https://rahat.up.nic.in/",
    "Page Title": "Office of Relief Commissioner | Uttar Pradesh | Lucknow",
    "Twitter": "https://x.com/rahat_up/",
    "Facebook": "https://www.facebook.com/UpRahatAyukt/",
    "Instagram": "https://www.instagram.com/rahat_up/",
    "Last Update": "2025-07-25 17:03:29.173642+00:00"
  },
  {
    "Source URL": "https://rahat.up.nic.in/upcovidcarefund.aspx/",
    "Page Title": "Office of Relief Commissioner | Uttar Pradesh | Lucknow",
    "Twitter": "https://x.com/rahat_up/",
    "Facebook": "https://www.facebook.com/UpRahatAyukt/",
    "Instagram": "https://www.instagram.com/rahat_up/",
    "Last Update": "2025-07-25 17:03:32.361282+00:00"
  },
  {
    "Source URL": "https://sec.up.nic.in/",
    "Page Title": "State Election Commission::UP",
    "Phone": [
      "0522 - 2630130",
      "1234567891",
      "0522- 2630115"
    ],
    "Email": [
      "secup@up.nic.in"
    ],
    "Last Update": "2025-07-25 17:03:30.447533+00:00"
  },
  {
    "Source URL": "https://sewayojan.up.nic.in/",
    "Page Title": "Rojgaar Sangam",
    "Phone": [
      "0522-2630690"
    ],
    "Email": [
      "sewayojan-up@gov.in"
    ],
    "Last Update": "2025-07-25 17:03:29.571845+00:00"
  },
  {
    "Source URL": "https://up.nic.in/",
    "Page Title": "NIC Uttar Pradesh State Centre | Driving ICT in Uttar Pradesh | India",
    "Twitter": "https://twitter.com/NICMeity",
    "Facebook": "https://www.facebook.com/NICIndia",
    "Last Update": "2025-07-25 17:03:22.165369+00:00"
  },
  {
    "Source URL": "https://uparchives.up.nic.in/",
    "Page Title": "Uttar Pradesh State Archives",
    "Twitter": "https://twitter.com/StateArchives",
    "Facebook": "https://www.facebook.com/UP-State-Archives-Lucknow-India-793317834090129/",
    "Instagram": "https://www.instagram.com/upstatearchives/",
    "YouTube": "https://www.youtube.com/channel/UCcUgrSoDTotJBC9HLdt6zzw",
    "Email": [
      "uparchives.lko@gmail.com"
    ],
    "Last Update": "2025-07-25 17:03:29.912838+00:00"
  },
  {
    "Source URL": "https://uphrc.up.nic.in/",
    "Page Title": "Uttar Pradesh Human Rights Commission",
    "Phone": [
      "1800180310"
    ],
    "Email": [
      "uphrclko@yahoo.co.in"
    ],
    "Last Update": "2025-07-25 17:03:30.227830+00:00"
  }
]